workplace_client/__init__.py
workplace_client/api_client.py
workplace_client/api_response.py
workplace_client/configuration.py
workplace_client/exceptions.py
workplace_client/py.typed
workplace_client/rest.py
workplace_client/api/__init__.py
workplace_client/api/available_packages_api.py
workplace_client/api/change_quota_api.py
workplace_client/api/create_alias_api.py
workplace_client/api/delete_alias_api.py
workplace_client/api/delete_email_api.py
workplace_client/api/dns_info_api.py
workplace_client/api/domain_alias_api.py
workplace_client/api/domain_api.py
workplace_client/api/domain_info_api.py
workplace_client/api/get_token_api.py
workplace_client/api/import_api.py
workplace_client/api/refresh_token_api.py
workplace_client/api/reset_password_api.py
workplace_client/api/subscription_info_api.py
workplace_client/api/subscriptions_api.py
workplace_client/api/update_email_quota_api.py
workplace_client/api/upgrade_api.py
workplace_client/models/__init__.py
workplace_client/models/alias_display.py
workplace_client/models/change_email_quota.py
workplace_client/models/change_quota_create200_response.py
workplace_client/models/delete_alias.py
workplace_client/models/delete_email.py
workplace_client/models/dns_info_create200_response.py
workplace_client/models/dns_info_create200_response_found_dns.py
workplace_client/models/dns_info_create_request.py
workplace_client/models/dns_info_request.py
workplace_client/models/dns_info_response.py
workplace_client/models/dns_record.py
workplace_client/models/domain.py
workplace_client/models/domain_action.py
workplace_client/models/email_alias.py
workplace_client/models/email_display.py
workplace_client/models/found_dns_records.py
workplace_client/models/import_create_request.py
workplace_client/models/open_exchange_create_account.py
workplace_client/models/order_display.py
workplace_client/models/password_reset.py
workplace_client/models/reset_email_password.py
workplace_client/models/service_action.py
truehost_workplace_api_client-1.0.26.dist-info/METADATA
truehost_workplace_api_client-1.0.26.dist-info/WHEEL
truehost_workplace_api_client-1.0.26.dist-info/top_level.txt
truehost_workplace_api_client-1.0.26.dist-info/RECORD
