Metadata-Version: 2.4
Name: truehost-workplace-api-client
Version: 1.0.26
Summary: Workplace Console API
Home-page: https://github.com/truehostcloud/workplace-python-client
Author: OpenAPI Generator community
Author-email: support@truehost.cloud
Keywords: OpenAPI,OpenAPI-Generator,Workplace Console API
Requires-Dist: urllib3<3.0.0,>=2.1.0
Requires-Dist: python-dateutil>=2.8.2
Requires-Dist: pydantic>=2
Requires-Dist: typing-extensions>=4.7.1
Dynamic: author
Dynamic: author-email
Dynamic: description
Dynamic: description-content-type
Dynamic: home-page
Dynamic: keywords
Dynamic: requires-dist
Dynamic: summary
